riscv_assembler/__init__.py
riscv_assembler/convert.py
riscv_assembler/instr_arr.py
riscv_assembler/parse.py
riscv_assembler/data/instr_data.dat
riscv_assembler/data/reg_map.dat
riscv_assembler-1.2.1.dist-info/LICENSE
riscv_assembler-1.2.1.dist-info/METADATA
riscv_assembler-1.2.1.dist-info/WHEEL
riscv_assembler-1.2.1.dist-info/entry_points.txt
riscv_assembler-1.2.1.dist-info/top_level.txt
riscv_assembler-1.2.1.dist-info/RECORD
