Metadata-Version: 2.1
Name: riscv-assembler
Version: 1.2.1
Summary: RISC-V Assembly code assembler package for Python.
Home-page: https://github.com/celebi-pkg/riscv-assembler
Author: Kaya Celebi
Author-email: kayacelebi17@gmail.com
Project-URL: Bug Tracker, https://github.com/celebi-pkg/riscv-assembler/issues
Project-URL: Changelog, https://github.com/celebi-pkg/riscv-assembler/releases
Classifier: Programming Language :: Python :: 3
Classifier: License :: OSI Approved :: MIT License
Classifier: Intended Audience :: Developers
Requires-Python: >=3.6
License-File: LICENSE
